{
  "versions": [
    {
      "version": "1.2.0",
      "date": "Ιούλιος 2025",
      "changes": [
        {
          "type": "new",
          "emoji": "✨",
          "text": "Πλήρης εκσυγχρονισμός UI με νέο σύστημα σχεδιασμού"
        },
        {
          "type": "new",
          "emoji": "📊",
          "text": "Διαδραστικός πίνακας ελέγχου με στατιστικά διακομιστή και πρόσφατους συνδέσμους"
        },
        {
          "type": "new",
          "emoji": "🌍",
          "text": "Προστέθηκε υποστήριξη για 6 νέες γλώσσες: ελληνικά, ιταλικά, ολλανδικά, πολωνικά, πορτογαλικά, σουηδικά"
        },
        {
          "type": "improved",
          "emoji": "🎨",
          "text": "Βελτιωμένη προσβασιμότητα με πλοήγηση πληκτρολογίου και υποστήριξη αναγνώστη οθόνης"
        },
        {
          "type": "improved",
          "emoji": "🌍",
          "text": "Βελτιωμένη διεθνοποίηση με 14+ γλώσσες και υποστήριξη RTL"
        },
        {
          "type": "fixed",
          "emoji": "🐛",
          "text": "Διορθώθηκαν προβλήματα CORS με αιτήματα API του σεναρίου παρασκηνίου"
        }
      ]
    },
    {
      "version": "1.1.0",
      "date": "Μάρτιος 2025",
      "changes": [
        {
          "type": "new",
          "emoji": "🌍",
          "text": "Προστέθηκε υποστήριξη αραβικής γλώσσας με διάταξη RTL"
        },
        {
          "type": "new",
          "emoji": "🌍",
          "text": "Προστέθηκε απλοποιημένη κινεζική τοπικοποίηση"
        },
        {
          "type": "new",
          "emoji": "ℹ️",
          "text": "Εμφάνιση πληροφοριών έκδοσης στο υποσέλιδο"
        },
        {
          "type": "improved",
          "emoji": "⚙️",
          "text": "Βελτιωμένες επιλογές διαμόρφωσης διακομιστή YOURLS"
        },
        {
          "type": "improved",
          "emoji": "🎨",
          "text": "Βελτιώσεις στη σειρά γλωσσών και προσαρμογές στυλ"
        }
      ]
    },
    {
      "version": "1.0.0",
      "date": "Μάρτιος 2025",
      "changes": [
        {
          "type": "new",
          "emoji": "🚀",
          "text": "Αρχική έκδοση με υποστήριξη Manifest V3"
        },
        {
          "type": "new",
          "emoji": "🔗",
          "text": "Βασική λειτουργία συντόμευσης URL"
        },
        {
          "type": "new",
          "emoji": "🔄",
          "text": "Υποστήριξη πολλαπλών διακομιστών για εναλλαγή μεταξύ περιπτώσεων YOURLS"
        },
        {
          "type": "new",
          "emoji": "📋",
          "text": "Λειτουργία αντιγραφής με ένα κλικ για συντομευμένα URL"
        },
        {
          "type": "new",
          "emoji": "🎯",
          "text": "Ενσωμάτωση μενού περιβάλλοντος για συντόμευση συνδέσμων"
        },
        {
          "type": "new",
          "emoji": "⚙️",
          "text": "Ρυθμίσεις διαμόρφωσης για διακομιστή YOURLS και προτιμήσεις"
        }
      ]
    }
  ]
}
